<?xml version='1.0' standalone='yes'?>

<impress>

<header>Linux Nedir ?</header>
<author>Gökmen GÖKSEL</author>
<email>gokmen@pardus.org.tr</email>
<firm>TÜBİTAK/UEKAE - Pardus Projesi</firm>

    <page>
        <header>Linux Nedir ?</header>
        <content>
          /vcenter/
            Gökmen GÖKSEL /br/
            /c:blue/ gokmen@pardus.org.tr //c/ /br/
            TÜBİTAK UEKAE
          //vcenter/
        </content>
    </page>

    <page>
        <header>Tarih</header>
        <content>
            /- 1984 Özgür Yazılım Akımı (GNU)
            /-- Richard STALLMAN, GNU is Not UNIX
            /- 1985 Özgür Yazılım Vakfı (FSF)
            /-- Free Software Foundation, GPL
            /- 1991 Linux Çekirdeği
            /-- Linus TORVALDS
            /- 1992 GNU/Linux Dağıtımları
            /-- Slackware(1992),Debian(1992),RedHat(1995),Pardus(2005) ...
        </content>
    </page>

    <page>
        <header>Kavramlar</header>
        <content>
            /- Özgür Yazılım
            /- Açık Kaynak
            /- Genel Kamu Lisansı (GPL)
            /- Çekirdek
            /- Linux
            /- Dağıtım
            /- Pardus
        </content>
    </page>

    <page>
        <header>Özgür Yazılım</header>
        <content>
            /- Yazılımın özgürü ?
            /-- Buradaki özgürlük kodu değiştirme özgürlüğünü temel alır.
            /-- Yazılımı satma özgürlüğüne kadar gider.
            /- Özgür yazılım ihtiyacı ?
            /-- Tekerleği tekrar icat etmek gerekir mi ?
            /-- Kalite.
        </content>
    </page>

    <page>
        <header>Açık Kaynak</header>
        <content>
            /- Yazılımın kaynak kodları yazılım ile birlikte verilir.
            /-- Kodları değiştirmek yasaldır.
            /- Yazılımın adını değiştirip o yazılımı istediğiniz fiyata satmak da yasaldır.
            /- Yazılıma birşeyler eklemek,katkıda bulunmak serbesttir.
            /-- Yazarın hakları korunmalıdır.
            /-- Koda yaptığınız eklemeleri de halka açmalısınız.
        </content>
    </page>

    <page>
        <header>Genel Kamu Lisansı (GPL)</header>
        <content>
            /- Yazarın haklarını gözetmek için çıkarılmıştır.
            /- Özgürlüklerin Hukuksal tanımını içerir.
            /- Bu bir lisanstır:
            /-- Bazı çevreler "Özgür Yazılım" için "Lisansız Yazılım" derler, Yanlıştır; /br/
                Özgür Yazılımlar genelde GPL ya da buna benzer diğer Lisanslara (LGPL,BSD..) sahiptirler.
            /- Bu lisansın kopyalanması da serbesttir.
        </content>
    </page>

    <page>
        <header>Çekirdek (Kernel)</header>
        <content>
            /- İşletim sisteminin en önemli alt(kök) yazılımıdır.
            /- Donanımın ve Süreç kontrolünden/yönetiminden sorumludur;
            /-- Süreçlerin işlemciyi nasıl ve ne zaman kullanacağına karar verir.
            /-- Süreçlerin ihtiyacı olan bellekleme işlemini düzenler.
            /-- Yazılımların donanımlardan faydalanabilmesi için gerekli arayüzü oluşturur.
            /- Linux'ta bir çekirdektir.
        </content>
    </page>

    <page>
        <header>Linux</header>
        <content>
            /- 1991 yılında Linus TORVALDS tarafından özgürce geliştirilmek üzere ilk sürümü yayınlandı.
            /-- İlk sürüm sadece 80386 IBM PC'ler ile uyumlu olmasına rağmen şu anda buzdolaplarında dahi kullanılabiliyor.
            /--- Itanium, MIPS, SPARC, Motorola, PowerPC gibi platformlar da desteklenmekte.
            /- Linux bir işletim sistemi değildir;
            /-- GNU/Linux adı verilen ve GNU ekibi tarafından yazılmış sistem taban uygulamalarını kullanan işletim sisteminin çekirdeğidir.
            /- Linux İngilizce bir kelime değildir ve "Linhuks" şeklinde okunur.
            /- Detaylı bilgi ve kaynak kodu /c:blue/ www.kernel.org //c/ adresinden alınabilir.
        </content>
    </page>

    <page>
        <header>Sorular - Teşekkürler</header>
        <content>
          /vcenter/ 
            /c:green/ SORULAR ? //c/
          //vcenter/
        </content>
    </page>


</impress>
