<PISI>
	<Components>
		<Component>
			<Name>system</Name>
			<LocalName xml:lang="en">FIXME</LocalName>
            <Summary xml:lang="en">FIXME</Summary>
            <Description xml:lang="en">FIXME</Description>
            <Group>system</Group>
            <Maintainer>
                <Name>COMAK TEAM</Name>
                <Email>comak@comu.edu.tr</Email>
            </Maintainer>
        </Component>
		<Component>
			<Name>system.base</Name>
			<LocalName xml:lang="en">FIXME</LocalName>
            <Summary xml:lang="en">FIXME</Summary>
            <Description xml:lang="en">FIXME</Description>
            <Group>system</Group>
            <Maintainer>
                <Name>COMAK TEAM</Name>
                <Email>comak@comu.edu.tr</Email>
            </Maintainer>
        </Component>
		<Component>
			<Name>programming</Name>
			<LocalName xml:lang="en">FIXME</LocalName>
            <Summary xml:lang="en">FIXME</Summary>
            <Description xml:lang="en">FIXME</Description>
            <Group>programming</Group>
            <Maintainer>
                <Name>COMAK TEAM</Name>
                <Email>comak@comu.edu.tr</Email>
            </Maintainer>
        </Component>
		<Component>
			<Name>programming.language</Name>
			<LocalName xml:lang="en">FIXME</LocalName>
            <Summary xml:lang="en">FIXME</Summary>
            <Description xml:lang="en">FIXME</Description>
            <Group>programming</Group>
            <Maintainer>
                <Name>COMAK TEAM</Name>
                <Email>comak@comu.edu.tr</Email>
            </Maintainer>
        </Component>
		<Component>
			<Name>programming.language.python</Name>
			<LocalName xml:lang="en">FIXME</LocalName>
            <Summary xml:lang="en">FIXME</Summary>
            <Description xml:lang="en">FIXME</Description>
            <Group>programming</Group>
            <Maintainer>
                <Name>COMAK TEAM</Name>
                <Email>comak@comu.edu.tr</Email>
            </Maintainer>
        </Component>
		<Component>
			<Name>desktop</Name>
			<LocalName xml:lang="en">FIXME</LocalName>
            <Summary xml:lang="en">FIXME</Summary>
            <Description xml:lang="en">FIXME</Description>
            <Group>desktop</Group>
            <Maintainer>
                <Name>COMAK TEAM</Name>
                <Email>comak@comu.edu.tr</Email>
            </Maintainer>
        </Component>
		<Component>
			<Name>desktop.comak</Name>
			<LocalName xml:lang="en">FIXME</LocalName>
            <Summary xml:lang="en">FIXME</Summary>
            <Description xml:lang="en">FIXME</Description>
            <Group>desktop</Group>
            <Maintainer>
                <Name>Kaan Özdinçer</Name>
                <Email>kaanozdincer@gmail.com</Email>
            </Maintainer>
        </Component>
		<Component>
			<Name>desktop.gnome</Name>
			<LocalName xml:lang="en">FIXME</LocalName>
            <Summary xml:lang="en">FIXME</Summary>
            <Description xml:lang="en">FIXME</Description>
            <Group>desktop</Group>
            <Maintainer>
                <Name>COMAK TEAM</Name>
                <Email>comak@comu.edu.tr</Email>
            </Maintainer>
        </Component>
		<Component>
			<Name>desktop.gnome.base</Name>
			<LocalName xml:lang="en">FIXME</LocalName>
            <Summary xml:lang="en">FIXME</Summary>
            <Description xml:lang="en">FIXME</Description>
            <Group>desktop</Group>
            <Maintainer>
                <Name>COMAK TEAM</Name>
                <Email>comak@comu.edu.tr</Email>
            </Maintainer>
        </Component>
		<Component>
			<Name>desktop.gnome.addon</Name>
			<LocalName xml:lang="en">FIXME</LocalName>
            <Summary xml:lang="en">FIXME</Summary>
            <Description xml:lang="en">FIXME</Description>
            <Group>desktop</Group>
            <Maintainer>
                <Name>COMAK TEAM</Name>
                <Email>comak@comu.edu.tr</Email>
            </Maintainer>
        </Component>
		<Component>
			<Name>desktop.gnome.extra</Name>
			<LocalName xml:lang="en">FIXME</LocalName>
            <Summary xml:lang="en">FIXME</Summary>
            <Description xml:lang="en">FIXME</Description>
            <Group>desktop</Group>
            <Maintainer>
                <Name>COMAK TEAM</Name>
                <Email>comak@comu.edu.tr</Email>
            </Maintainer>
        </Component>
		<Component>
			<Name>desktop.gnome.externalpackages</Name>
			<LocalName xml:lang="en">FIXME</LocalName>
            <Summary xml:lang="en">FIXME</Summary>
            <Description xml:lang="en">FIXME</Description>
            <Group>desktop</Group>
            <Maintainer>
                <Name>COMAK TEAM</Name>
                <Email>comak@comu.edu.tr</Email>
            </Maintainer>
        </Component>
		<Component>
			<Name>desktop.lxde</Name>
			<LocalName xml:lang="en">FIXME</LocalName>
            <Summary xml:lang="en">FIXME</Summary>
            <Description xml:lang="en">FIXME</Description>
            <Group>desktop</Group>
            <Maintainer>
                <Name>COMAK TEAM</Name>
                <Email>comak@comu.edu.tr</Email>
            </Maintainer>
        </Component>
		<Component>
			<Name>desktop.lxde.base</Name>
			<LocalName xml:lang="en">FIXME</LocalName>
            <Summary xml:lang="en">FIXME</Summary>
            <Description xml:lang="en">FIXME</Description>
            <Group>desktop</Group>
            <Maintainer>
                <Name>COMAK TEAM</Name>
                <Email>comak@comu.edu.tr</Email>
            </Maintainer>
        </Component>
		<Component>
			<Name>desktop.lxde.addon</Name>
			<LocalName xml:lang="en">FIXME</LocalName>
            <Summary xml:lang="en">FIXME</Summary>
            <Description xml:lang="en">FIXME</Description>
            <Group>desktop</Group>
            <Maintainer>
                <Name>COMAK TEAM</Name>
                <Email>comak@comu.edu.tr</Email>
            </Maintainer>
        </Component>
		<Component>
			<Name>desktop.fluxbox</Name>
			<LocalName xml:lang="en">FIXME</LocalName>
            <Summary xml:lang="en">FIXME</Summary>
            <Description xml:lang="en">FIXME</Description>
            <Group>desktop</Group>
            <Maintainer>
                <Name>COMAK TEAM</Name>
                <Email>comak@comu.edu.tr</Email>
            </Maintainer>
        </Component>
		<Component>
			<Name>desktop.fluxbox.base</Name>
			<LocalName xml:lang="en">FIXME</LocalName>
            <Summary xml:lang="en">FIXME</Summary>
            <Description xml:lang="en">FIXME</Description>
            <Group>desktop</Group>
            <Maintainer>
                <Name>COMAK TEAM</Name>
                <Email>comak@comu.edu.tr</Email>
            </Maintainer>
        </Component>
		<Component>
			<Name>desktop.fluxbox.addon</Name>
			<LocalName xml:lang="en">FIXME</LocalName>
            <Summary xml:lang="en">FIXME</Summary>
            <Description xml:lang="en">FIXME</Description>
            <Group>desktop</Group>
            <Maintainer>
                <Name>COMAK TEAM</Name>
                <Email>comak@comu.edu.tr</Email>
            </Maintainer>
        </Component>
		<Component>
			<Name>desktop.enlightenment</Name>
			<LocalName xml:lang="en">FIXME</LocalName>
            <Summary xml:lang="en">FIXME</Summary>
            <Description xml:lang="en">FIXME</Description>
            <Group>desktop</Group>
            <Maintainer>
                <Name>COMAK TEAM</Name>
                <Email>comak@comu.edu.tr</Email>
            </Maintainer>
        </Component>
		<Component>
			<Name>desktop.enlightenment.base</Name>
			<LocalName xml:lang="en">FIXME</LocalName>
            <Summary xml:lang="en">FIXME</Summary>
            <Description xml:lang="en">FIXME</Description>
            <Group>desktop</Group>
            <Maintainer>
                <Name>COMAK TEAM</Name>
                <Email>comak@comu.edu.tr</Email>
            </Maintainer>
        </Component>
		<Component>
			<Name>desktop.enlightenment.addon</Name>
			<LocalName xml:lang="en">FIXME</LocalName>
            <Summary xml:lang="en">FIXME</Summary>
            <Description xml:lang="en">FIXME</Description>
            <Group>desktop</Group>
            <Maintainer>
                <Name>COMAK TEAM</Name>
                <Email>comak@comu.edu.tr</Email>
            </Maintainer>
        </Component>
		<Component>
			<Name>desktop.xfce</Name>
			<LocalName xml:lang="en">FIXME</LocalName>
            <Summary xml:lang="en">FIXME</Summary>
            <Description xml:lang="en">FIXME</Description>
            <Group>desktop</Group>
            <Maintainer>
                <Name>Alper Tekinalp</Name>
                <Email>alper.tekinalp@gmail.com</Email>
            </Maintainer>
        </Component>
		<Component>
			<Name>desktop.xfce.base</Name>
			<LocalName xml:lang="en">FIXME</LocalName>
            <Summary xml:lang="en">FIXME</Summary>
            <Description xml:lang="en">FIXME</Description>
            <Group>desktop</Group>
            <Maintainer>
                <Name>Alper Tekinalp</Name>
                <Email>alper.tekinalp@gmail.com</Email>
            </Maintainer>
        </Component>
		<Component>
			<Name>desktop.xfce.addon</Name>
			<LocalName xml:lang="en">FIXME</LocalName>
            <Summary xml:lang="en">FIXME</Summary>
            <Description xml:lang="en">FIXME</Description>
            <Group>desktop</Group>
            <Maintainer>
                <Name>Alper Tekinalp</Name>
                <Email>alper.tekinalp@gmail.com</Email>
            </Maintainer>
        </Component>
		<Component>
			<Name>desktop.xfce.lookandfeel</Name>
			<LocalName xml:lang="en">FIXME</LocalName>
            <Summary xml:lang="en">FIXME</Summary>
            <Description xml:lang="en">FIXME</Description>
            <Group>desktop</Group>
            <Maintainer>
                <Name>Alper Tekinalp</Name>
                <Email>alper.tekinalp@gmail.com</Email>
            </Maintainer>
        </Component>
		<Component>
			<Name>desktop.xfce.admin</Name>
			<LocalName xml:lang="en">FIXME</LocalName>
            <Summary xml:lang="en">FIXME</Summary>
            <Description xml:lang="en">FIXME</Description>
            <Group>desktop</Group>
            <Maintainer>
                <Name>Alper Tekinalp</Name>
                <Email>alper.tekinalp@gmail.com</Email>
            </Maintainer>
        </Component>
		<Component>
			<Name>desktop.gnome3</Name>
			<LocalName xml:lang="en">FIXME</LocalName>
            <Summary xml:lang="en">FIXME</Summary>
            <Description xml:lang="en">FIXME</Description>
            <Group>desktop</Group>
            <Maintainer>
                <Name>COMAK TEAM</Name>
                <Email>comak@comu.edu.tr</Email>
            </Maintainer>
        </Component>
		<Component>
			<Name>desktop.gnome3.base</Name>
			<LocalName xml:lang="en">FIXME</LocalName>
            <Summary xml:lang="en">FIXME</Summary>
            <Description xml:lang="en">FIXME</Description>
            <Group>desktop</Group>
            <Maintainer>
                <Name>COMAK TEAM</Name>
                <Email>comak@comu.edu.tr</Email>
            </Maintainer>
        </Component>
		<Component>
			<Name>desktop.gnome3.addon</Name>
			<LocalName xml:lang="en">FIXME</LocalName>
            <Summary xml:lang="en">FIXME</Summary>
            <Description xml:lang="en">FIXME</Description>
            <Group>desktop</Group>
            <Maintainer>
                <Name>COMAK TEAM</Name>
                <Email>comak@comu.edu.tr</Email>
            </Maintainer>
        </Component>
	</Components>
</PISI>
